xplainit/__init__.py
xplainit/explanation.py
xplainit-0.4.dist-info/LICENSE
xplainit-0.4.dist-info/METADATA
xplainit-0.4.dist-info/WHEEL
xplainit-0.4.dist-info/top_level.txt
xplainit-0.4.dist-info/RECORD
