Metadata-Version: 2.1
Name: xplainit
Version: 0.4
Summary: A library to generate natural language explanations of ML model predictions
Home-page: https://github.com/
Author: Leandre Nash
Author-email: leandrework@gmail.com
License: MIT
License-File: LICENSE
Requires-Dist: numpy
Requires-Dist: scikit-learn
Requires-Dist: matplotlib
